FlowWork/Server.zip
FlowWork/__init__.py
FlowWork/common.py
FlowWork/Net/__init__.py
FlowWork/Net/flownet.py
FlowWork/Server/__init__.py
FlowWork/Server/flow/__init__.py
FlowWork/Server/flow/controller.py
FlowWork/Server/flow/main.py
FlowWork/Server/flow/manifest.py
FlowWork/Server/flow/model.py
FlowWork/Server/flow/setting.py
FlowWork/Server/flow/ui.py
FlowWork/Server/flow/static/bootstrap/dist/css/bootstrap-theme.css
FlowWork/Server/flow/static/bootstrap/dist/css/bootstrap-theme.css.map
FlowWork/Server/flow/static/bootstrap/dist/css/bootstrap-theme.min.css
FlowWork/Server/flow/static/bootstrap/dist/css/bootstrap.css
FlowWork/Server/flow/static/bootstrap/dist/css/bootstrap.css.map
FlowWork/Server/flow/static/bootstrap/dist/css/bootstrap.min.css
FlowWork/Server/flow/static/bootstrap/dist/js/bootstrap.js
FlowWork/Server/flow/static/bootstrap/dist/js/bootstrap.min.js
FlowWork/Server/flow/static/bootstrap/grunt/bs-glyphicons-data-generator.js
FlowWork/Server/flow/static/bootstrap/grunt/bs-lessdoc-parser.js
FlowWork/Server/flow/static/bootstrap/grunt/bs-raw-files-generator.js
FlowWork/Server/flow/static/bootstrap/grunt/sauce_browsers.yml
FlowWork/Server/flow/static/bootstrap/js/affix.js
FlowWork/Server/flow/static/bootstrap/js/alert.js
FlowWork/Server/flow/static/bootstrap/js/button.js
FlowWork/Server/flow/static/bootstrap/js/carousel.js
FlowWork/Server/flow/static/bootstrap/js/collapse.js
FlowWork/Server/flow/static/bootstrap/js/dropdown.js
FlowWork/Server/flow/static/bootstrap/js/modal.js
FlowWork/Server/flow/static/bootstrap/js/popover.js
FlowWork/Server/flow/static/bootstrap/js/scrollspy.js
FlowWork/Server/flow/static/bootstrap/js/tab.js
FlowWork/Server/flow/static/bootstrap/js/tooltip.js
FlowWork/Server/flow/static/bootstrap/js/transition.js
FlowWork/Server/flow/static/bootstrap/less/alerts.less
FlowWork/Server/flow/static/bootstrap/less/badges.less
FlowWork/Server/flow/static/bootstrap/less/bootstrap.less
FlowWork-0.7.dist-info/DESCRIPTION.rst
FlowWork-0.7.dist-info/METADATA
FlowWork-0.7.dist-info/RECORD
FlowWork-0.7.dist-info/WHEEL
FlowWork-0.7.dist-info/entry_points.txt
FlowWork-0.7.dist-info/metadata.json
FlowWork-0.7.dist-info/top_level.txt
