Metadata-Version: 2.0
Name: FlowWork
Version: 0.7
Summary: a simple way to use mongo db, let db like dict
Home-page: https://github.com/Qingluan/.git
Author: Qing luan
Author-email: darkhackdevil@gmail.com
License: MIT
Platform: UNKNOWN
Requires-Dist: SocialKit
